modparc/__init__.py
modparc/parse.py
modparc/specification.py
modparc/syntax/__init__.py
modparc/syntax/class_definition.py
modparc/syntax/component_clause.py
modparc/syntax/equations.py
modparc/syntax/expressions.py
modparc/syntax/extends.py
modparc/syntax/modification.py
modparc/syntax/stored_definition.py
modparc/syntax/syntax_elements.py
modparc-0.2.1.dist-info/DESCRIPTION.rst
modparc-0.2.1.dist-info/METADATA
modparc-0.2.1.dist-info/RECORD
modparc-0.2.1.dist-info/WHEEL
modparc-0.2.1.dist-info/metadata.json
modparc-0.2.1.dist-info/top_level.txt
