Metadata-Version: 2.0
Name: modparc
Version: 0.2.1
Summary: A Modelica parser based on parser generator
Home-page: https://github.com/xie-dongping/modparc
Author: 谢东平 Dongping XIE
Author-email: dongping.xie.tud@gmail.com
License: GNU General Public License v3
Keywords: modparc
Platform: UNKNOWN
Classifier: Development Status :: 2 - Pre-Alpha
Classifier: Intended Audience :: Developers
Classifier: Intended Audience :: Science/Research
Classifier: Topic :: Scientific/Engineering
Classifier: License :: OSI Approved :: GNU General Public License v3 (GPLv3)
Classifier: Natural Language :: English
Classifier: Programming Language :: Python :: 2
Classifier: Programming Language :: Python :: 2.7
Classifier: Programming Language :: Python :: 3
Classifier: Programming Language :: Python :: 3.3
Classifier: Programming Language :: Python :: 3.4
Classifier: Programming Language :: Python :: 3.5
Requires-Dist: funcparserlib
